QAWebServer/QA_Web.py
QAWebServer/__init__.py
QAWebServer/basehandles.py
QAWebServer/commandhandler.py
QAWebServer/filehandler.py
QAWebServer/schedulehandler.py
QAWebServer/userhandles.py
QAWebServer/util.py
quantaxis_webserver-2.0.0.dist-info/LICENSE
quantaxis_webserver-2.0.0.dist-info/METADATA
quantaxis_webserver-2.0.0.dist-info/WHEEL
quantaxis_webserver-2.0.0.dist-info/entry_points.txt
quantaxis_webserver-2.0.0.dist-info/top_level.txt
quantaxis_webserver-2.0.0.dist-info/zip-safe
quantaxis_webserver-2.0.0.dist-info/RECORD
