Metadata-Version: 2.1
Name: quantaxis-webserver
Version: 2.0.0
Summary: QUANTAXIS WEBSERVER: WEBSERVER FOR QUANTAXIS
Home-page: https://github.com/yutiansut/quantaxis_webserver
Author: yutiansut
Author-email: yutiansut@qq.com
License: MIT
Keywords: quantaxis,quant,finance,Backtest,Framework
Platform: UNKNOWN
Classifier: License :: OSI Approved :: MIT License
Classifier: Programming Language :: Python
Classifier: Intended Audience :: Developers
Classifier: Operating System :: OS Independent
Requires-Dist: tornado (>=6.1)
Requires-Dist: qaenv
Requires-Dist: apscheduler
Requires-Dist: quantaxis (>=1.7.0)
